{
  "generatedAt": "2026-03-24T16:56:38.608Z",
  "seedBatchId": "company_seed_2026-03-24T16-56-33-448Z",
  "projectId": "recommendation-engine-70f6d",
  "companies": [
    {
      "companyName": "SeedWave 01 Systems",
      "email": "hiring.seedwave-01@smallco.dev",
      "password": null,
      "uid": "seedco_1774371393450_001",
      "jobsCreated": 6,
      "accountCreated": false,
      "authStatus": "seed-writer-only"
    },
    {
      "companyName": "SeedWave 02 Systems",
      "email": "hiring.seedwave-02@smallco.dev",
      "password": null,
      "uid": "seedco_1774371393450_002",
      "jobsCreated": 6,
      "accountCreated": false,
      "authStatus": "seed-writer-only"
    },
    {
      "companyName": "SeedWave 03 Systems",
      "email": "hiring.seedwave-03@smallco.dev",
      "password": null,
      "uid": "seedco_1774371393450_003",
      "jobsCreated": 6,
      "accountCreated": false,
      "authStatus": "seed-writer-only"
    },
    {
      "companyName": "SeedWave 04 Systems",
      "email": "hiring.seedwave-04@smallco.dev",
      "password": null,
      "uid": "seedco_1774371393450_004",
      "jobsCreated": 6,
      "accountCreated": false,
      "authStatus": "seed-writer-only"
    },
    {
      "companyName": "SeedWave 05 Systems",
      "email": "hiring.seedwave-05@smallco.dev",
      "password": null,
      "uid": "seedco_1774371393450_005",
      "jobsCreated": 6,
      "accountCreated": false,
      "authStatus": "seed-writer-only"
    },
    {
      "companyName": "SeedWave 06 Systems",
      "email": "hiring.seedwave-06@smallco.dev",
      "password": null,
      "uid": "seedco_1774371393450_006",
      "jobsCreated": 6,
      "accountCreated": false,
      "authStatus": "seed-writer-only"
    },
    {
      "companyName": "SeedWave 07 Systems",
      "email": "hiring.seedwave-07@smallco.dev",
      "password": null,
      "uid": "seedco_1774371393450_007",
      "jobsCreated": 6,
      "accountCreated": false,
      "authStatus": "seed-writer-only"
    },
    {
      "companyName": "SeedWave 08 Systems",
      "email": "hiring.seedwave-08@smallco.dev",
      "password": null,
      "uid": "seedco_1774371393450_008",
      "jobsCreated": 6,
      "accountCreated": false,
      "authStatus": "seed-writer-only"
    },
    {
      "companyName": "SeedWave 09 Systems",
      "email": "hiring.seedwave-09@smallco.dev",
      "password": null,
      "uid": "seedco_1774371393450_009",
      "jobsCreated": 6,
      "accountCreated": false,
      "authStatus": "seed-writer-only"
    },
    {
      "companyName": "SeedWave 10 Systems",
      "email": "hiring.seedwave-10@smallco.dev",
      "password": null,
      "uid": "seedco_1774371393450_010",
      "jobsCreated": 6,
      "accountCreated": false,
      "authStatus": "seed-writer-only"
    },
    {
      "companyName": "SeedWave 11 Systems",
      "email": "hiring.seedwave-11@smallco.dev",
      "password": null,
      "uid": "seedco_1774371393450_011",
      "jobsCreated": 6,
      "accountCreated": false,
      "authStatus": "seed-writer-only"
    },
    {
      "companyName": "SeedWave 12 Systems",
      "email": "hiring.seedwave-12@smallco.dev",
      "password": null,
      "uid": "seedco_1774371393450_012",
      "jobsCreated": 6,
      "accountCreated": false,
      "authStatus": "seed-writer-only"
    },
    {
      "companyName": "SeedWave 13 Systems",
      "email": "hiring.seedwave-13@smallco.dev",
      "password": null,
      "uid": "seedco_1774371393450_013",
      "jobsCreated": 6,
      "accountCreated": false,
      "authStatus": "seed-writer-only"
    },
    {
      "companyName": "SeedWave 14 Systems",
      "email": "hiring.seedwave-14@smallco.dev",
      "password": null,
      "uid": "seedco_1774371393450_014",
      "jobsCreated": 6,
      "accountCreated": false,
      "authStatus": "seed-writer-only"
    },
    {
      "companyName": "SeedWave 15 Systems",
      "email": "hiring.seedwave-15@smallco.dev",
      "password": null,
      "uid": "seedco_1774371393450_015",
      "jobsCreated": 6,
      "accountCreated": false,
      "authStatus": "seed-writer-only"
    },
    {
      "companyName": "SeedWave 16 Systems",
      "email": "hiring.seedwave-16@smallco.dev",
      "password": null,
      "uid": "seedco_1774371393450_016",
      "jobsCreated": 6,
      "accountCreated": false,
      "authStatus": "seed-writer-only"
    },
    {
      "companyName": "SeedWave 17 Systems",
      "email": "hiring.seedwave-17@smallco.dev",
      "password": null,
      "uid": "seedco_1774371393450_017",
      "jobsCreated": 6,
      "accountCreated": false,
      "authStatus": "seed-writer-only"
    },
    {
      "companyName": "SeedWave 18 Systems",
      "email": "hiring.seedwave-18@smallco.dev",
      "password": null,
      "uid": "seedco_1774371393450_018",
      "jobsCreated": 6,
      "accountCreated": false,
      "authStatus": "seed-writer-only"
    },
    {
      "companyName": "SeedWave 19 Systems",
      "email": "hiring.seedwave-19@smallco.dev",
      "password": null,
      "uid": "seedco_1774371393450_019",
      "jobsCreated": 6,
      "accountCreated": false,
      "authStatus": "seed-writer-only"
    },
    {
      "companyName": "SeedWave 20 Systems",
      "email": "hiring.seedwave-20@smallco.dev",
      "password": null,
      "uid": "seedco_1774371393450_020",
      "jobsCreated": 6,
      "accountCreated": false,
      "authStatus": "seed-writer-only"
    },
    {
      "companyName": "SeedWave 21 Systems",
      "email": "hiring.seedwave-21@smallco.dev",
      "password": null,
      "uid": "seedco_1774371393450_021",
      "jobsCreated": 6,
      "accountCreated": false,
      "authStatus": "seed-writer-only"
    },
    {
      "companyName": "SeedWave 22 Systems",
      "email": "hiring.seedwave-22@smallco.dev",
      "password": null,
      "uid": "seedco_1774371393450_022",
      "jobsCreated": 6,
      "accountCreated": false,
      "authStatus": "seed-writer-only"
    },
    {
      "companyName": "SeedWave 23 Systems",
      "email": "hiring.seedwave-23@smallco.dev",
      "password": null,
      "uid": "seedco_1774371393450_023",
      "jobsCreated": 6,
      "accountCreated": false,
      "authStatus": "seed-writer-only"
    },
    {
      "companyName": "SeedWave 24 Systems",
      "email": "hiring.seedwave-24@smallco.dev",
      "password": null,
      "uid": "seedco_1774371393450_024",
      "jobsCreated": 6,
      "accountCreated": false,
      "authStatus": "seed-writer-only"
    },
    {
      "companyName": "SeedWave 25 Systems",
      "email": "hiring.seedwave-25@smallco.dev",
      "password": null,
      "uid": "seedco_1774371393450_025",
      "jobsCreated": 6,
      "accountCreated": false,
      "authStatus": "seed-writer-only"
    },
    {
      "companyName": "SeedWave 26 Systems",
      "email": "hiring.seedwave-26@smallco.dev",
      "password": null,
      "uid": "seedco_1774371393450_026",
      "jobsCreated": 6,
      "accountCreated": false,
      "authStatus": "seed-writer-only"
    },
    {
      "companyName": "SeedWave 27 Systems",
      "email": "hiring.seedwave-27@smallco.dev",
      "password": null,
      "uid": "seedco_1774371393450_027",
      "jobsCreated": 6,
      "accountCreated": false,
      "authStatus": "seed-writer-only"
    },
    {
      "companyName": "SeedWave 28 Systems",
      "email": "hiring.seedwave-28@smallco.dev",
      "password": null,
      "uid": "seedco_1774371393450_028",
      "jobsCreated": 6,
      "accountCreated": false,
      "authStatus": "seed-writer-only"
    },
    {
      "companyName": "SeedWave 29 Systems",
      "email": "hiring.seedwave-29@smallco.dev",
      "password": null,
      "uid": "seedco_1774371393450_029",
      "jobsCreated": 6,
      "accountCreated": false,
      "authStatus": "seed-writer-only"
    },
    {
      "companyName": "SeedWave 30 Systems",
      "email": "hiring.seedwave-30@smallco.dev",
      "password": null,
      "uid": "seedco_1774371393450_030",
      "jobsCreated": 6,
      "accountCreated": false,
      "authStatus": "seed-writer-only"
    },
    {
      "companyName": "SeedWave 31 Systems",
      "email": "hiring.seedwave-31@smallco.dev",
      "password": null,
      "uid": "seedco_1774371393450_031",
      "jobsCreated": 6,
      "accountCreated": false,
      "authStatus": "seed-writer-only"
    },
    {
      "companyName": "SeedWave 32 Systems",
      "email": "hiring.seedwave-32@smallco.dev",
      "password": null,
      "uid": "seedco_1774371393450_032",
      "jobsCreated": 6,
      "accountCreated": false,
      "authStatus": "seed-writer-only"
    },
    {
      "companyName": "SeedWave 33 Systems",
      "email": "hiring.seedwave-33@smallco.dev",
      "password": null,
      "uid": "seedco_1774371393450_033",
      "jobsCreated": 6,
      "accountCreated": false,
      "authStatus": "seed-writer-only"
    },
    {
      "companyName": "SeedWave 34 Systems",
      "email": "hiring.seedwave-34@smallco.dev",
      "password": null,
      "uid": "seedco_1774371393450_034",
      "jobsCreated": 6,
      "accountCreated": false,
      "authStatus": "seed-writer-only"
    },
    {
      "companyName": "SeedWave 35 Systems",
      "email": "hiring.seedwave-35@smallco.dev",
      "password": null,
      "uid": "seedco_1774371393450_035",
      "jobsCreated": 6,
      "accountCreated": false,
      "authStatus": "seed-writer-only"
    },
    {
      "companyName": "SeedWave 36 Systems",
      "email": "hiring.seedwave-36@smallco.dev",
      "password": null,
      "uid": "seedco_1774371393450_036",
      "jobsCreated": 6,
      "accountCreated": false,
      "authStatus": "seed-writer-only"
    },
    {
      "companyName": "SeedWave 37 Systems",
      "email": "hiring.seedwave-37@smallco.dev",
      "password": null,
      "uid": "seedco_1774371393450_037",
      "jobsCreated": 6,
      "accountCreated": false,
      "authStatus": "seed-writer-only"
    },
    {
      "companyName": "SeedWave 38 Systems",
      "email": "hiring.seedwave-38@smallco.dev",
      "password": null,
      "uid": "seedco_1774371393450_038",
      "jobsCreated": 6,
      "accountCreated": false,
      "authStatus": "seed-writer-only"
    },
    {
      "companyName": "SeedWave 39 Systems",
      "email": "hiring.seedwave-39@smallco.dev",
      "password": null,
      "uid": "seedco_1774371393450_039",
      "jobsCreated": 6,
      "accountCreated": false,
      "authStatus": "seed-writer-only"
    },
    {
      "companyName": "SeedWave 40 Systems",
      "email": "hiring.seedwave-40@smallco.dev",
      "password": null,
      "uid": "seedco_1774371393450_040",
      "jobsCreated": 6,
      "accountCreated": false,
      "authStatus": "seed-writer-only"
    },
    {
      "companyName": "SeedWave 41 Systems",
      "email": "hiring.seedwave-41@smallco.dev",
      "password": null,
      "uid": "seedco_1774371393450_041",
      "jobsCreated": 6,
      "accountCreated": false,
      "authStatus": "seed-writer-only"
    },
    {
      "companyName": "SeedWave 42 Systems",
      "email": "hiring.seedwave-42@smallco.dev",
      "password": null,
      "uid": "seedco_1774371393450_042",
      "jobsCreated": 6,
      "accountCreated": false,
      "authStatus": "seed-writer-only"
    },
    {
      "companyName": "SeedWave 43 Systems",
      "email": "hiring.seedwave-43@smallco.dev",
      "password": null,
      "uid": "seedco_1774371393450_043",
      "jobsCreated": 6,
      "accountCreated": false,
      "authStatus": "seed-writer-only"
    },
    {
      "companyName": "SeedWave 44 Systems",
      "email": "hiring.seedwave-44@smallco.dev",
      "password": null,
      "uid": "seedco_1774371393450_044",
      "jobsCreated": 6,
      "accountCreated": false,
      "authStatus": "seed-writer-only"
    },
    {
      "companyName": "SeedWave 45 Systems",
      "email": "hiring.seedwave-45@smallco.dev",
      "password": null,
      "uid": "seedco_1774371393450_045",
      "jobsCreated": 6,
      "accountCreated": false,
      "authStatus": "seed-writer-only"
    },
    {
      "companyName": "SeedWave 46 Systems",
      "email": "hiring.seedwave-46@smallco.dev",
      "password": null,
      "uid": "seedco_1774371393450_046",
      "jobsCreated": 6,
      "accountCreated": false,
      "authStatus": "seed-writer-only"
    },
    {
      "companyName": "SeedWave 47 Systems",
      "email": "hiring.seedwave-47@smallco.dev",
      "password": null,
      "uid": "seedco_1774371393450_047",
      "jobsCreated": 6,
      "accountCreated": false,
      "authStatus": "seed-writer-only"
    },
    {
      "companyName": "SeedWave 48 Systems",
      "email": "hiring.seedwave-48@smallco.dev",
      "password": null,
      "uid": "seedco_1774371393450_048",
      "jobsCreated": 6,
      "accountCreated": false,
      "authStatus": "seed-writer-only"
    },
    {
      "companyName": "SeedWave 49 Systems",
      "email": "hiring.seedwave-49@smallco.dev",
      "password": null,
      "uid": "seedco_1774371393450_049",
      "jobsCreated": 6,
      "accountCreated": false,
      "authStatus": "seed-writer-only"
    },
    {
      "companyName": "SeedWave 50 Systems",
      "email": "hiring.seedwave-50@smallco.dev",
      "password": null,
      "uid": "seedco_1774371393450_050",
      "jobsCreated": 6,
      "accountCreated": false,
      "authStatus": "seed-writer-only"
    }
  ]
}